sensirion_uart_svm4x/__init__.py
sensirion_uart_svm4x/commands.py
sensirion_uart_svm4x/device.py
sensirion_uart_svm4x/response_provider.py
sensirion_uart_svm4x/result_types.py
sensirion_uart_svm4x/version.py
sensirion_uart_svm4x-2.0.3.dist-info/LICENSE
sensirion_uart_svm4x-2.0.3.dist-info/METADATA
sensirion_uart_svm4x-2.0.3.dist-info/WHEEL
sensirion_uart_svm4x-2.0.3.dist-info/top_level.txt
sensirion_uart_svm4x-2.0.3.dist-info/RECORD
