Metadata-Version: 2.1
Name: sensirion-uart-svm4x
Version: 2.0.3
Summary: SHDLC driver for the Sensirion SVM4X sensor family
Home-page: UNKNOWN
Author: Sensirion
Author-email: info@sensirion.com
License: BSD
Project-URL: Documentation, https://sensirion.github.io/python-uart-svm4x
Project-URL: Repository, https://github.com/Sensirion/python-uart-svm4x
Project-URL: Changelog, https://github.com/Sensirion/python-uart-svm4x/blob/master/CHANGELOG.rst
Keywords: Sensirion SVM4X
Platform: UNKNOWN
Classifier: Intended Audience :: Developers
Classifier: License :: Other/Proprietary License
Classifier: Programming Language :: Python :: 3.6
Classifier: Programming Language :: Python :: 3.8
Classifier: Topic :: Software Development :: Libraries :: Python Modules
Requires-Python: >=3.6, <4
Requires-Dist: sensirion-shdlc-driver (~=0.1.5)
Requires-Dist: sensirion-driver-adapters (<3.0,>=2.1.8)
Requires-Dist: sensirion-driver-support-types (~=0.2.0)
Provides-Extra: docs
Requires-Dist: click (==8.0.4) ; extra == 'docs'
Requires-Dist: jinja2 (==3.0.1) ; extra == 'docs'
Requires-Dist: sphinx (~=2.2.1) ; extra == 'docs'
Requires-Dist: sphinx-rtd-theme (~=0.4.3) ; extra == 'docs'
Provides-Extra: test
Requires-Dist: flake8 (~=3.7.8) ; extra == 'test'
Requires-Dist: pytest (~=6.2.5) ; extra == 'test'
Requires-Dist: pytest-cov (~=3.0.0) ; extra == 'test'
